setup.py
Tasos_test_python_package/Binomialdistribution.py
Tasos_test_python_package/Gaussiandistribution.py
Tasos_test_python_package/Generaldistribution.py
Tasos_test_python_package/__init__.py
Tasos_test_python_package.egg-info/PKG-INFO
Tasos_test_python_package.egg-info/SOURCES.txt
Tasos_test_python_package.egg-info/dependency_links.txt
Tasos_test_python_package.egg-info/not-zip-safe
Tasos_test_python_package.egg-info/top_level.txt